crplog/__init__.py
crplog/extractor.py
crplog/initial.py
crplog/main.py
crplog-0.1.6.dist-info/WHEEL
crplog-0.1.6.dist-info/METADATA
crplog-0.1.6.dist-info/RECORD
