Metadata-Version: 2.1
Name: crplog
Version: 0.1.6
Summary: 
Author: mjaquier
Author-email: mjaquier@mjaquier.xyz
Requires-Python: >=3.8,<4.0
Classifier: Programming Language :: Python :: 3
Classifier: Programming Language :: Python :: 3.8
Classifier: Programming Language :: Python :: 3.9
Requires-Dist: aihelper (>=0.2.4,<0.3.0)
Requires-Dist: aitkhelp (>=0.1.0,<0.2.0)
Requires-Dist: pandas (>=1.1.2,<2.0.0)
Requires-Dist: xlrd (>=1.2.0,<2.0.0)
